{ "compressionlevel":-1,
 "editorsettings":
    {
     "export":
        {
         "target":"."
        }
    },
 "height":135,
 "infinite":false,
 "layers":[
        {
         "color":"#000000",
         "draworder":"topdown",
         "id":2,
         "name":"wall",
         "objects":[
                {
                 "height":56,
                 "id":7,
                 "name":"",
                 "rotation":0,
                 "type":"",
                 "visible":true,
                 "width":1248,
                 "x":744,
                 "y":600
                }, 
                {
                 "height":72,
                 "id":80,
                 "name":"",
                 "rotation":0,
                 "type":"",
                 "visible":true,
                 "width":1992,
                 "x":-72,
                 "y":0
                }, 
                {
                 "height":312,
                 "id":81,
                 "name":"",
                 "rotation":0,
                 "type":"",
                 "visible":true,
                 "width":120,
                 "x":1872,
                 "y":72
                }, 
                {
                 "height":168,
                 "id":98,
                 "name":"",
                 "rotation":0,
                 "type":"",
                 "visible":true,
                 "width":32,
                 "x":1616,
                 "y":432
                }, 
                {
                 "height":168,
                 "id":102,
                 "name":"",
                 "rotation":0,
                 "type":"",
                 "visible":true,
                 "width":32,
                 "x":1224,
                 "y":432
                }, 
                {
                 "height":168,
                 "id":103,
                 "name":"",
                 "rotation":0,
                 "type":"",
                 "visible":true,
                 "width":32,
                 "x":792,
                 "y":432
                }, 
                {
                 "height":792,
                 "id":104,
                 "name":"",
                 "rotation":0,
                 "type":"",
                 "visible":true,
                 "width":168,
                 "x":-72,
                 "y":288
                }, 
                {
                 "height":336,
                 "id":105,
                 "name":"",
                 "rotation":0,
                 "type":"",
                 "visible":true,
                 "width":232,
                 "x":96,
                 "y":432
                }, 
                {
                 "height":128,
                 "id":106,
                 "name":"",
                 "rotation":0,
                 "type":"",
                 "visible":true,
                 "width":1568,
                 "x":96,
                 "y":1024
                }, 
                {
                 "height":496,
                 "id":107,
                 "name":"",
                 "rotation":0,
                 "type":"",
                 "visible":true,
                 "width":48,
                 "x":1872,
                 "y":656
                }],
         "opacity":1,
         "type":"objectgroup",
         "visible":true,
         "x":0,
         "y":0
        }, 
        {
         "draworder":"topdown",
         "id":5,
         "name":"ref",
         "objects":[
                {
                 "height":128,
                 "id":4,
                 "name":"Player",
                 "rotation":0,
                 "type":"",
                 "visible":true,
                 "width":40,
                 "x":1352,
                 "y":720
                }, 
                {
                 "height":392,
                 "id":42,
                 "name":"Wall Jump",
                 "rotation":0,
                 "type":"",
                 "visible":true,
                 "width":232,
                 "x":1336,
                 "y":200
                }, 
                {
                 "height":200,
                 "id":101,
                 "name":"Jump",
                 "rotation":0,
                 "type":"",
                 "visible":true,
                 "width":480,
                 "x":320,
                 "y":232
                }],
         "opacity":1,
         "type":"objectgroup",
         "visible":true,
         "x":0,
         "y":0
        }, 
        {
         "color":"#ffaa00",
         "draworder":"topdown",
         "id":6,
         "name":"trigger",
         "objects":[
                {
                 "height":264,
                 "id":79,
                 "name":"",
                 "rotation":0,
                 "type":"",
                 "visible":true,
                 "width":80,
                 "x":976,
                 "y":760
                }],
         "opacity":1,
         "type":"objectgroup",
         "visible":true,
         "x":0,
         "y":0
        }, 
        {
         "color":"#5555ff",
         "draworder":"topdown",
         "id":7,
         "name":"gate",
         "objects":[
                {
                 "height":216,
                 "id":30,
                 "name":"",
                 "rotation":0,
                 "type":"",
                 "visible":true,
                 "width":32,
                 "x":1880,
                 "y":384
                }, 
                {
                 "height":216,
                 "id":94,
                 "name":"",
                 "rotation":0,
                 "type":"",
                 "visible":true,
                 "width":32,
                 "x":8,
                 "y":72
                }, 
                {
                 "height":24,
                 "id":108,
                 "name":"",
                 "rotation":0,
                 "type":"",
                 "visible":true,
                 "width":80,
                 "x":504,
                 "y":824
                }, 
                {
                 "height":24,
                 "id":109,
                 "name":"",
                 "rotation":0,
                 "type":"",
                 "visible":true,
                 "width":80,
                 "x":504,
                 "y":624
                }, 
                {
                 "height":24,
                 "id":110,
                 "name":"",
                 "rotation":0,
                 "type":"",
                 "visible":true,
                 "width":208,
                 "x":1664,
                 "y":1032
                }],
         "opacity":1,
         "type":"objectgroup",
         "visible":true,
         "x":0,
         "y":0
        }, 
        {
         "color":"#ff0000",
         "draworder":"topdown",
         "id":3,
         "name":"enemy",
         "objects":[
                {
                 "height":0,
                 "id":92,
                 "name":"",
                 "point":true,
                 "rotation":0,
                 "type":"",
                 "visible":true,
                 "width":0,
                 "x":216,
                 "y":1024
                }, 
                {
                 "height":0,
                 "id":93,
                 "name":"",
                 "point":true,
                 "rotation":0,
                 "type":"",
                 "visible":true,
                 "width":0,
                 "x":1024,
                 "y":600
                }, 
                {
                 "height":0,
                 "id":99,
                 "name":"",
                 "point":true,
                 "rotation":0,
                 "type":"",
                 "visible":true,
                 "width":0,
                 "x":1416,
                 "y":600
                }, 
                {
                 "height":0,
                 "id":112,
                 "name":"",
                 "point":true,
                 "rotation":0,
                 "type":"",
                 "visible":true,
                 "width":0,
                 "x":944,
                 "y":1024
                }, 
                {
                 "height":0,
                 "id":113,
                 "name":"",
                 "point":true,
                 "rotation":0,
                 "type":"",
                 "visible":true,
                 "width":0,
                 "x":1640,
                 "y":1024
                }],
         "opacity":1,
         "type":"objectgroup",
         "visible":true,
         "x":0,
         "y":0
        }, 
        {
         "color":"#ffff00",
         "draworder":"topdown",
         "id":4,
         "name":"door",
         "objects":[
                {
                 "height":216,
                 "id":13,
                 "name":"",
                 "rotation":0,
                 "type":"",
                 "visible":true,
                 "width":56,
                 "x":-72,
                 "y":72
                }, 
                {
                 "height":216,
                 "id":87,
                 "name":"",
                 "rotation":0,
                 "type":"",
                 "visible":true,
                 "width":56,
                 "x":1936,
                 "y":384
                }, 
                {
                 "height":56,
                 "id":111,
                 "name":"",
                 "rotation":0,
                 "type":"",
                 "visible":true,
                 "width":208,
                 "x":1664,
                 "y":1096
                }],
         "opacity":1,
         "type":"objectgroup",
         "visible":true,
         "x":0,
         "y":0
        }],
 "nextlayerid":8,
 "nextobjectid":115,
 "orientation":"orthogonal",
 "properties":[
        {
         "name":"canMirror",
         "type":"bool",
         "value":true
        }],
 "renderorder":"right-down",
 "tiledversion":"1.4.2",
 "tileheight":8,
 "tilesets":[],
 "tilewidth":8,
 "type":"map",
 "version":1.4,
 "width":240
}